async_rotating_proxy/__init__.py
async_rotating_proxy/browser.py
async_rotating_proxy-0.0.6.dist-info/METADATA
async_rotating_proxy-0.0.6.dist-info/WHEEL
async_rotating_proxy-0.0.6.dist-info/licenses/LICENSE.txt
async_rotating_proxy-0.0.6.dist-info/RECORD
