Metadata-Version: 2.1
Name: async_rotating_proxy
Version: 0.0.6
Summary: Run an API on your local machine that reroutes traffic through rotating proxies. Useful for pyppeteer proxy rotation.
Project-URL: Homepage, https://github.com/gbiz123/async-rotating-proxy
Author-email: Greg Bizup <g.bizup@gmail.com>
License-File: LICENSE.txt
Keywords: fastapi,proxy,pyppeteer,rotating proxy,scraping
Classifier: License :: OSI Approved :: MIT License
Classifier: Operating System :: OS Independent
Classifier: Programming Language :: Python :: 3
Requires-Python: >3.10
Requires-Dist: aiohttp>=3.8.4
Requires-Dist: fake-headers>=1.0.2
Requires-Dist: fastapi>=0.95.1
Requires-Dist: pyppeteer>=1.0.2
Requires-Dist: uvicorn>=0.21.1
